indices_api/__init__.py
indices_api/client.py
pypi_indices_api-0.3.dist-info/METADATA
pypi_indices_api-0.3.dist-info/WHEEL
pypi_indices_api-0.3.dist-info/top_level.txt
pypi_indices_api-0.3.dist-info/RECORD
