Metadata-Version: 2.4
Name: pypi-indices-api
Version: 0.3
Summary: A Python package to get the latest indices from the Indices-API
Home-page: https://github.com/Zyla-Labs/pypi-indices-api
Author: zylalabs
Author-email: hello@zylalabs.com
Keywords: indices-api,precious Indicesapi,Indicesapi,Indices,precious Indices,gold,silver,Platinum,Palladium,Ruthenium,Rhodium,forex data,rates,money,usd,eur,btc,forex api,gbp to usd,gbp to eur,eur to usd,api,currency api,exchange rate api,get currency rates api,currency rates php,usd to eur api,copper,nickel,aluminium,TIN,Zinc
Dynamic: author
Dynamic: author-email
Dynamic: description
Dynamic: description-content-type
Dynamic: home-page
Dynamic: keywords
Dynamic: summary
